waldur_site_agent_harbor/__init__.py
waldur_site_agent_harbor/backend.py
waldur_site_agent_harbor/client.py
waldur_site_agent_harbor/exceptions.py
waldur_site_agent_harbor-0.8.2.dist-info/METADATA
waldur_site_agent_harbor-0.8.2.dist-info/WHEEL
waldur_site_agent_harbor-0.8.2.dist-info/entry_points.txt
waldur_site_agent_harbor-0.8.2.dist-info/RECORD
