Metadata-Version: 2.4
Name: waldur-site-agent-harbor
Version: 0.8.2
Summary: Harbor container registry plugin for Waldur Site Agent
Author-email: OpenNode Team <info@opennodecloud.com>
Requires-Python: <4,>=3.9
Requires-Dist: requests>=2.31.0
Requires-Dist: waldur-site-agent>=0.7.0
